<databaseChangeLog
        xmlns="http://www.liquibase.org/xml/ns/dbchangelog"
        xmlns:ext="http://www.liquibase.org/xml/ns/dbchangelog-ext"
        xmlns:xsi="http://www.w3.org/2001/XMLSchema-instance"
        xsi:schemaLocation="http://www.liquibase.org/xml/ns/dbchangelog-ext
   http://www.liquibase.org/xml/ns/dbchangelog/dbchangelog-ext.xsd
   http://www.liquibase.org/xml/ns/dbchangelog
   http://www.liquibase.org/xml/ns/dbchangelog/dbchangelog-3.4.xsd">
    <include file="db/changelog/0.0.1/roll_tables_init.xml"/>
    <include file="db/changelog/0.0.1/product_tables_init.xml"/>
    <include file="db/changelog/0.0.1/roll_tables_f_keys.xml"/>
    <include file="db/changelog/0.0.1/product_tables_f_keys.xml"/>
    <include file="db/changelog/0.1.0/task_details_table_init.xml"/>
    <include file="db/changelog/0.0.3/order_tables_init.xml"/>
    <include file="db/changelog/0.0.3/order_tables_f_keys.xml"/>
    <include file="db/changelog/0.0.2/norm_tables_init.xml"/>
    <include file="db/changelog/0.0.2/norm_tables_f_keys.xml"/>
    <include file="db/changelog/0.2.0/user_tables_init.xml"/>
    <include file="db/changelog/0.2.0/user_tables_f_keys.xml"/>
    <include file="db/changelog/0.2.0/user_tables_populate.xml"/>
    <include file="db/changelog/0.0.4/plan_tables_init.xml"/>
    <include file="db/changelog/0.0.4/plan_tables_f_keys.xml"/>
    <include file="db/changelog/0.0.5/table_modification_tables_init.xml"/>
    <include file="db/changelog/0.0.5/table_modification_tables_f_key.xml"/>
    <include file="db/changelog/0.0.5/table_modification_tables_populate.xml"/>
</databaseChangeLog>